{"dispatcher":{"bulk":{"completed":301,"max_elapsed_ms":4,"over_1s_count":0,"over_30s_count":0,"over_5s_count":0,"received":301,"timed_out":0,"total_elapsed_ns":160071975},"membership":{"completed":11940,"max_elapsed_ms":5025,"over_1s_count":59,"over_30s_count":0,"over_5s_count":13,"received":11953,"timed_out":13,"total_elapsed_ns":221922669519},"pubsub":{"completed":50297,"max_elapsed_ms":1431,"over_1s_count":4,"over_30s_count":0,"over_5s_count":0,"received":50313,"timed_out":0,"total_elapsed_ns":11437982940367},"pubsub_workers":16,"recv_depth":{"bulk":{"capacity":4000,"latest":0,"max":0},"membership":{"capacity":4000,"latest":0,"max":120},"pubsub":{"capacity":10000,"latest":9996,"max":10000}}},"ok":true,"pubsub_stages":{"decode":{"count":56762,"max_ns":11470191,"over_1s_count":0,"over_30s_count":0,"over_5s_count":0,"total_ns":1351509871},"dedupe_check":{"count":50312,"max_ns":15699950,"over_1s_count":0,"over_30s_count":0,"over_5s_count":0,"total_ns":1187929626},"dedupe_lock_acquire":{"count":50312,"max_ns":21655497,"over_1s_count":0,"over_30s_count":0,"over_5s_count":0,"total_ns":232260929},"eager_fanout":{"count":20075,"max_ns":16908707,"over_1s_count":0,"over_30s_count":0,"over_5s_count":0,"total_ns":498602992},"message_kinds":{"anti_entropy":496,"decode_failed":0,"eager":43864,"graft":74,"ihave":5058,"iwant":895,"other":0,"prune":8668},"republish":{"count":24000,"max_ns":1428304405,"over_1s_count":4,"over_30s_count":0,"over_5s_count":0,"total_ns":11412235834822},"republish_per_peer_timeout":12520,"verify":{"count":44360,"max_ns":24630331,"over_1s_count":0,"over_30s_count":0,"over_5s_count":0,"total_ns":21276359362}},"recv_pump":{"bulk":{"avg_dwell_ms":0,"capacity":4000,"consumer_per_sec":0.31947571160791866,"dequeued_total":301,"dropped_closed":0,"dropped_full":0,"enqueued_total":301,"latest_depth":1,"max_depth":1,"max_dwell_ms":0,"produced_total":301,"producer_per_sec":0.31947571160791866},"membership":{"avg_dwell_ms":413,"capacity":4000,"consumer_per_sec":12.68668830846994,"dequeued_total":11953,"dropped_closed":0,"dropped_full":0,"enqueued_total":11953,"latest_depth":1,"max_depth":121,"max_dwell_ms":13173,"produced_total":11953,"producer_per_sec":12.68668830846994},"per_peer":{"0b7bb5a3b9951f8a6301bebcc499b1ac2dbd93d1185bf19bc109066145380c5c":{"bulk_dropped_full":0,"bulk_produced":30,"membership_dropped_full":0,"membership_produced":1534,"pubsub_dropped_full":27095,"pubsub_produced":41017},"11d167d8442575e837eb45fc4859155ffaccc149a50bf6cf22268853175636c3":{"bulk_dropped_full":0,"bulk_produced":30,"membership_dropped_full":0,"membership_produced":1853,"pubsub_dropped_full":6439,"pubsub_produced":11379},"16f0bf0337c634edfdcf8aadcdd5968d2d33abbf0ac2a47c3467106164e2d22c":{"bulk_dropped_full":0,"bulk_produced":31,"membership_dropped_full":0,"membership_produced":1482,"pubsub_dropped_full":12019,"pubsub_produced":21743},"6a24bdeddd828e1e859b63d72f0dae635557c5f21207b4bac5f24aa3ed54376e":{"bulk_dropped_full":0,"bulk_produced":32,"membership_dropped_full":0,"membership_produced":1412,"pubsub_dropped_full":10643,"pubsub_produced":17614},"b2606ba6db0d98b34c589426beacde5ebe965e5dbc8ba95b8c771e93bdf0db76":{"bulk_dropped_full":0,"bulk_produced":29,"membership_dropped_full":0,"membership_produced":741,"pubsub_dropped_full":6268,"pubsub_produced":8411},"b7a23e48aae46082f9c952de2f225c7c4bafeee50fea88ef50c51bd0a6c47ce8":{"bulk_dropped_full":0,"bulk_produced":31,"membership_dropped_full":0,"membership_produced":1491,"pubsub_dropped_full":19470,"pubsub_produced":28395},"c1dfdbd98799fc47eb593ee72cb482d8d66aeb5d7ec38da130fbac31ad3d42c7":{"bulk_dropped_full":0,"bulk_produced":31,"membership_dropped_full":0,"membership_produced":591,"pubsub_dropped_full":7,"pubsub_produced":14},"c75da0889d51c4260e32df88e866fb258891abb475e13d5d1163f3394a2f97cd":{"bulk_dropped_full":0,"bulk_produced":25,"membership_dropped_full":0,"membership_produced":304,"pubsub_dropped_full":0,"pubsub_produced":2},"dc090fd3d05888a3b6228cdfce54830d4140e5332248087c9b04284161619b31":{"bulk_dropped_full":0,"bulk_produced":32,"membership_dropped_full":0,"membership_produced":1890,"pubsub_dropped_full":31446,"pubsub_produced":44607},"f480ac4007eca95e23eeadabccbc28000d5f2821610dc5ac1971864d81836d02":{"bulk_dropped_full":0,"bulk_produced":30,"membership_dropped_full":0,"membership_produced":655,"pubsub_dropped_full":574,"pubsub_produced":1089}},"pubsub":{"avg_dwell_ms":149501,"capacity":10000,"consumer_per_sec":53.40126736920004,"dequeued_total":50313,"dropped_closed":0,"dropped_full":113961,"enqueued_total":60310,"latest_depth":9997,"max_depth":10000,"max_dwell_ms":204197,"produced_total":174271,"producer_per_sec":184.9679459721714},"uptime_secs":942},"stats":{"decode_to_delivery_drops":0,"delivered_to_subscriber":15379,"in_flight_decode":0,"incoming_decode_failed":3,"incoming_decoded":15379,"incoming_total":15382,"publish_failed":0,"publish_total":1261,"slow_subscriber_dropped":0,"subscriber_channel_closed":0}}==SEP==
{"ok":true,"status":"healthy","version":"0.19.18","peers":10,"uptime_secs":942}
